source_punk_api/__init__.py
source_punk_api/manifest.yaml
source_punk_api/run.py
source_punk_api/schemas/beers.json
source_punk_api/schemas/beers_with_id.json
source_punk_api/source.py
source_punk_api/spec.yaml
airbyte_source_punk_api-0.1.5.dist-info/METADATA
airbyte_source_punk_api-0.1.5.dist-info/WHEEL
airbyte_source_punk_api-0.1.5.dist-info/entry_points.txt
airbyte_source_punk_api-0.1.5.dist-info/RECORD
